vilolog/__init__.py
vilolog/pageModel.py
vilolog/userModel.py
vilolog/utils.py
vilolog/vilolog.py
vilolog/default-admin-theme/admin-footer.html
vilolog/default-admin-theme/admin-head-common.html
vilolog/default-admin-theme/admin-header.html
vilolog/default-admin-theme/login.html
vilolog/default-admin-theme/page-editor.html
vilolog/default-admin-theme/page-lister.html
vilolog/default-admin-theme/reset.html
vilolog/default-admin-theme/setup.html
vilolog/default-admin-theme/user-editor.html
vilolog/default-admin-theme/user-lister.html
vilolog/default-admin-theme/static/admin-styles.css
vilolog/default-blog-theme/404.html
vilolog/default-blog-theme/blog-footer.html
vilolog/default-blog-theme/blog-head-common.html
vilolog/default-blog-theme/blog-header.html
vilolog/default-blog-theme/home.html
vilolog/default-blog-theme/page.html
vilolog/default-blog-theme/static/blog-styles.css
vilolog-0.0.7.dist-info/LICENSE.txt
vilolog-0.0.7.dist-info/WHEEL
vilolog-0.0.7.dist-info/METADATA
vilolog-0.0.7.dist-info/RECORD
