Metadata-Version: 2.1
Name: vilolog
Version: 0.0.7
Summary: ViloLog: Simple blogging engine, built atop Vilo and PogoDB.
Home-page: https://github.com/polydojo/vilolog
License: UNKNOWN
Author: Polydojo, Inc.
Author-email: 8079593+sumukhbarve@users.noreply.github.com
Classifier: License :: OSI Approved :: GNU General Public License v3 or later (GPLv3+)
Requires-Dist: bcrypt >=3.2.0
Requires-Dist: dotsi >=0.0.3
Requires-Dist: Markdown >=3.3.3
Requires-Dist: pogodb >=0.0.3
Requires-Dist: psycopg2-binary >=2.8.6
Requires-Dist: python-dateutil >=2.8.1
Requires-Dist: qree >=0.0.4
Requires-Dist: vilo >=0.0.5
